pxy/__init__.py
pxy/sub/__init__.py
pxy/sub/list_utils.py
pxy/sub/version_utils.py
tests/__init__.py
tests/test_list_utils.py
tests/test_version_utils.py
pxy-0.0.8.dist-info/LICENSE
pxy-0.0.8.dist-info/METADATA
pxy-0.0.8.dist-info/WHEEL
pxy-0.0.8.dist-info/top_level.txt
pxy-0.0.8.dist-info/RECORD
