Metadata-Version: 2.1
Name: pxy
Version: 0.0.8
Summary: tools of python
Home-page: https://github.com/foyoux/pxy
Author: foyou
Author-email: yimi.0822@qq.com
License: GPL-3.0
Project-URL: Documentation, https://pxy.readthedocs.io/zh_CN/latest/
Project-URL: Source, https://github.com/foyoux/pxy
Project-URL: Bug Tracker, https://github.com/foyoux/pxy/issues
Keywords: document translate tools
Platform: UNKNOWN
Classifier: Programming Language :: Python :: 3
Classifier: License :: OSI Approved :: GNU General Public License v3 (GPLv3)
Classifier: Operating System :: OS Independent
Classifier: Environment :: Console
Classifier: Intended Audience :: End Users/Desktop
Classifier: Natural Language :: Chinese (Simplified)
Classifier: Development Status :: 5 - Production/Stable
Requires-Python: >=3.6.*
License-File: LICENSE
